huaweicloudsdkclassroom/__init__.py
huaweicloudsdkclassroom/v3/__init__.py
huaweicloudsdkclassroom/v3/classroom_async_client.py
huaweicloudsdkclassroom/v3/classroom_client.py
huaweicloudsdkclassroom/v3/model/__init__.py
huaweicloudsdkclassroom/v3/model/apply_judgement_request.py
huaweicloudsdkclassroom/v3/model/apply_judgement_response.py
huaweicloudsdkclassroom/v3/model/classroom_card.py
huaweicloudsdkclassroom/v3/model/classroom_member.py
huaweicloudsdkclassroom/v3/model/difficult_info.py
huaweicloudsdkclassroom/v3/model/execute_exercise_request.py
huaweicloudsdkclassroom/v3/model/execute_exercise_response.py
huaweicloudsdkclassroom/v3/model/exercise_card.py
huaweicloudsdkclassroom/v3/model/exercise_case_resource.py
huaweicloudsdkclassroom/v3/model/exercise_code_resource.py
huaweicloudsdkclassroom/v3/model/exercise_detail_data.py
huaweicloudsdkclassroom/v3/model/exercise_filter.py
huaweicloudsdkclassroom/v3/model/exercise_group.py
huaweicloudsdkclassroom/v3/model/exercises_list_request_body.py
huaweicloudsdkclassroom/v3/model/job_card.py
huaweicloudsdkclassroom/v3/model/job_records.py
huaweicloudsdkclassroom/v3/model/judgement_case_info.py
huaweicloudsdkclassroom/v3/model/judgement_case_result.py
huaweicloudsdkclassroom/v3/model/judgement_result.py
huaweicloudsdkclassroom/v3/model/judgement_task_request_body.py
huaweicloudsdkclassroom/v3/model/knowledge_point_info.py
huaweicloudsdkclassroom/v3/model/knowledge_points_list_request_body.py
huaweicloudsdkclassroom/v3/model/list_all_difficults_request.py
huaweicloudsdkclassroom/v3/model/list_all_difficults_response.py
huaweicloudsdkclassroom/v3/model/list_classroom_member_jobs_request.py
huaweicloudsdkclassroom/v3/model/list_classroom_member_jobs_response.py
huaweicloudsdkclassroom/v3/model/list_classroom_members_request.py
huaweicloudsdkclassroom/v3/model/list_classroom_members_response.py
huaweicloudsdkclassroom/v3/model/list_classrooms_request.py
huaweicloudsdkclassroom/v3/model/list_classrooms_response.py
huaweicloudsdkclassroom-3.1.184.dist-info/METADATA
huaweicloudsdkclassroom-3.1.184.dist-info/WHEEL
huaweicloudsdkclassroom-3.1.184.dist-info/licenses/LICENSE
huaweicloudsdkclassroom-3.1.184.dist-info/RECORD
